dmt_magic/__init__.py
dmt_magic-1.1.1.dist-info/METADATA
dmt_magic-1.1.1.dist-info/WHEEL
dmt_magic-1.1.1.dist-info/licenses/LICENSE
dmt_magic-1.1.1.dist-info/RECORD
