Metadata-Version: 2.4
Name: dmt_magic
Version: 1.1.1
Summary: Jupyter Magic zur Integration des E-Assessment-Systems Data Management Tester (DMT)
Author-email: Andreas Thor <andreas.thor@htwk-leipzig.de>, Martin Petersohn <martin.petersohn@stud.htwk-leipzig.de>
License-File: LICENSE
Classifier: License :: OSI Approved :: MIT License
Classifier: Operating System :: OS Independent
Classifier: Programming Language :: Python :: 3
Requires-Python: >=3.9
Requires-Dist: markdown-it-py==3.0.0
